Workbook
Name CLASIFICACION: [1]PANEL!$D$11
Name SUELDOS: '[1]VALOR M.O.'!$B$6:$E$52

Sheet Resumen Oferta
B2: ANEXO N°
B3: Licitación Construcción OOCC Túnel LAT Vitacura - Providencia
B4: RESUMEN DE PRECIOS
C7: Ítem | D7: Total UF
C9: Resumen de Precios
B10: A | C10: Total Costo Directo | D10: =+'A) Detalle Costo Directo'!F360
B11: B | C11: Total Costo Indirecto | D11: =+'B) Detalle C. Ind., GG y Utilid'!G56
B12: C | C12: Total Gastos Generales | D12: =+'B) Detalle C. Ind., GG y Utilid'!G57
B13: D | C13: Utilidades | D13: =+'B) Detalle C. Ind., GG y Utilid'!G58
C15: Total Neto | D15: =+SUM(D10:D13)
C17: IVA | D17: =+D15*0.19
C19: Total | D19: =+D15+D17
D27: Firma y Timbre
D28: Representante Legal del Proponente
A32: Verde: cantidad calculada por modelo | B32: Salmón: precio referencial ONDAC 2026 (UF) | C32: Amarillo: completar con precio oferta

Sheet A) Detalle Costo Directo
A2: ANEXO N°
A3: =+'Resumen Oferta'!B3
A4: DESGLOSE DE COSTO DIRECTO
A6: N° | B6: Ítem | C6: Unidad | D6: Cantidad | E6: Precio Unitario UF | F6: =D6*E6 | G6: Observación | H6: Pago
A7: 1.0 | B7: Actividades Previas de Ingeniería, Procedimientos de Trabajo y Coordinación con Servicios de agua, electricidad, gas, telecomunicaciones | F7: =+SUM(F8:F12) | G7: x
A8: 1.1 | B8: Elaboración y Aprobación de todos los procedimientos de trabajo que sean necesarios para iniciar las obras: Correctas Prácticas con la Comunidad, Programa de Prevención de Riesgos, Habilitación de Instalación de Faenas, Construcción de Cierres Perimetrales, Ejecución de Señalización Vial, Plan de Emergencias, Matriz de Riesgos, Izaje Carga y Descarga y de Construcción Túnel Liner | C8: gl | D8: 1 | F8: =D8*E8 | G8: Etapa 1, Suma alzada
A9: 1.2 | B9: Revisión del Estudio de Levantamiento de Servicios aportado por STM. Comunicación inicial y coordinación con las empresas de servicios de agua, electricidad, telecomunicaciones, gas, la UOCT y municipalidades | C9: gl | D9: 1 | F9: =D9*E9 | G9: Etapa 1, Suma alzada
A10: 1.3 | B10: Memoria de Cálculo Sistema de Izaje y Fundación, Ventilación de Túnels (para construcción) | C10: gl | D10: 1 | F10: =D10*E10 | G10: Etapa 1, Suma alzada
A11: 1.4 | B11: Entrega de Planos As Built | C11: gl | D11: 1 | F11: =D11*E11 | G11: Etapa 2, Suma alzada
A13: 2.0 | B13: Suministros | F13: =+SUM(F14:F22)
A14: 2.1 | B14: Liners de Piques puesto en bodega del proveedor y aprobado por el Cliente (Piques de 4,0 metros de diámetro, espesor de liners de 5mm y galvanizado de 112 micras de espesor promedio) | C14: m | F14: =+D14*E14 | G14: Aporte STM | H14: 5% con el cumplimiento de Condiciones contractuales, 85% por avance proporcional y 10% con la recepción provisional de la obra.
A15: 2.2 | B15: Liners de Túnel puesto en bodega del proveedor y aprobado por el Cliente (2,21 metros de diámetro, espesor de liners de 5mm y galvanizado de 112 micras de espesor promedio) | C15: m | F15: =+D15*E15 | G15: Aporte STM
A16: 2.5 | B16: Jet Fan 3,5kW | C16: und | F16: =+D16*E16 | G16: Aporte STM
A17: 2.6 | B17: Estructuras Galvanizadas de soporte de cables | C17: kg | F17: =+D17*E17 | G17: Aporte STM
A18: 2.7 | B18: Estructuras de Cobertura de Piques | C18: kg | F18: =+D18*E18 | G18: Aporte STM
A19: 2.8 | B19: Estructuras Galvanizadas de Escalas, barandas y Plataformas | C19: kg | F19: =+D19*E19 | G19: Aporte STM
A20: 2.9 | B20: Otras Estructuras | C20: kg | F20: =+D20*E20 | G20: Aporte STM
A21: 2.10 | B21: Sistema de Planta Elevadora de Agua | C21: gl | F21: =+D21*E21 | G21: Aporte STM
A23: 3.0 | B23: Instalación de Faenas | F23: =+SUM(F24:F39)
A24: 3.1 | B24: Cierres Perimetrales Piques 02 a 08. Suministro, Retiro y Disposición final | C24: gl | D24: 1 | F24: =D24*E24 | G24: Etapa 2, Suma alzada | H24: 5% con el cumplimiento de Condiciones contractuales, 85% por avance proporcional y 10% con la recepción provisional de la obra
A25: 3.2 | B25: Portones Cierres Perimetrales Piques 02 a 08. Suministro, Retiro y Disposición final | C25: gl | D25: 1 | F25: =D25*E25 | G25: Etapa 2, Suma alzada
A26: 3.3 | B26: Bodegas Resnopel Piques 02 a 08 | C26: gl | D26: 1 | F26: =D26*E26 | G26: Etapa 2, Suma alzada
A27: 3.4 | B27: Bodegas Respel Piques 02 al 08 | C27: gl | D27: 1 | F27: =D27*E27 | G27: Etapa 2, Suma alzada
A28: 3.5 | B28: Contenedores Oficina, Bodega y Sala de Cambio Instalaciones de Faena Piques 01 a 08 | C28: gl | D28: 1 | F28: =D28*E28 | G28: Etapa 2, Suma alzada
A29: 3.6 | B29: Baños químicos Instalaciones de Faena Piques 01 a 08 | C29: gl | D29: 1 | F29: =D29*E29 | G29: Etapa 2, Suma alzada
A30: 3.7 | B30: Grupo generador Insonorizado e Instalación Eléctrica Piques 01 a 08 | C30: gl | D30: 1 | F30: =D30*E30 | G30: Etapa 2, Suma alzada
A31: 3.8 | B31: Estanque de recuperación de Agua de Lavado de Canoas, Piques 01 a 09 | C31: gl | D31: 1 | F31: =D31*E31 | G31: Etapa 2, Suma alzada
A32: 3.9 | B32: Instalación para Lavado de Ruedas Piques 02 a 08 | C32: gl | D32: 1 | F32: =D32*E32 | G32: Etapa 2, Suma alzada
A33: 3.10 | B33: Señaléticas, Extintores, Estaciones de Emergencia Piques 01 a 09 | C33: gl | D33: 1 | F33: =D33*E33 | G33: Etapa 2, Suma alzada
A34: 3.11 | B34: Fundación, estructura y equipos de Izaje (piques 01 a 09) | C34: gl | D34: 1 | F34: =D34*E34 | G34: Etapa 2, Suma alzada
A35: 3.12 | B35: Sistemas de Ventilación (piques 01 a 09) | C35: gl | D35: 1 | F35: =D35*E35 | G35: Etapa 2, Suma alzada
A36: 3.13 | B36: Implementación de Sistema de Rescate tipo Brazo pescante en Piques 01 a 09 | C36: gl | D36: 1 | F36: =D36*E36 | G36: Etapa 2, Suma alzada
... A38: 3.15 | B38: Otros elementos necesarios | C38: gl | D38: 1 | F38: =D38*E38 | G38: Etapa 2, Suma alzada
A40: 4.0 | B40: Obras Civiles Piques | F40: =+F41+F58+F74+F90+F106+F122+F138+F154+F170
A41: 4.1 | B41: Pique 1 Túnel Liner | F41: =+SUM(F42:F57)
A42: 4.1.1 | B42: Excavación | C42: m3 | D42: 252.46 | E42: 2.2078 | F42: =D42*E42 | G42: Etapa 2, Suma alzada | H42: 5% con el cumplimiento de Condiciones contractuales, 85% por avance proporcional y 10% con la recepción provisional de la obra.
A43: 4.1.2 | B43: Retiro excavación y transporte a botadero (geométrico) | C43: m3 | D43: 252.46 | E43: 0.9091 | F43: =D43*E43 | G43: Etapa 2, Suma alzada
A44: 4.1.3 | B44: Montaje Liner (Incluyendo sello entre placas y mortero) | C44: m | D44: 20.1 | E44: 5.7143 | F44: =D44*E44 | G44: Etapa 2, Suma alzada
A45: 4.1.4 | B45: Refuerzo Losa Anillo Fondo de Pique | C45: gl | D45: 1 | E45: 72.7273 | F45: =D45*E45 | G45: Etapa 2, Suma alzada
A46: 4.1.5 | B46: Construcción de Dren | C46: gl | D46: 1 | E46: 46.7532 | F46: =D46*E46 | G46: Etapa 2, Suma alzada
A47: 4.1.6 | B47: Terminaciones | C47: gl | D47: 1 | E47: 38.961 | F47: =D47*E47 | G47: Etapa 2, Suma alzada
A48: 4.1.7 | B48: Cobertura propia pique, considera construcción de Cámara de Conexión AT en SE Vitacura | C48: gl | D48: 1 | E48: 90.9091 | F48: =D48*E48 | G48: Etapa 2, Suma alzada
A49: 4.1.8 | B49: Montaje de Escalas y Plataforma | C49: gl | D49: 1 | E49: 83.1169 | F49: =D49*E49 | G49: Etapa 2, Suma alzada
A50: 4.1.9 | B50: Refuerzo Apertura Pique | C50: gl | D50: 1 | E50: 57.1429 | F50: =D50*E50 | G50: Etapa 2, Suma alzada
A51: 4.1.10 | B51: Shotcrete | C51: m3 | E51: 4.6753 | F51: =+D51*E51 | G51: Etapa 2, Suma alzada
A52: 4.1.11 | B52: Malla | C52: kg | E52: 0.0312 | F52: =+D52*E52 | G52: Etapa 2, Suma alzada
A53: 4.1.12 | B53: Instalación y Monitoreo de Pernos de Convergencia | C53: und | E53: 1.1688 | F53: =+D53*E53 | G53: Etapa 2, Suma alzada
A54: 4.1.13 | B54: Montaje estructura soporte de cables | C54: kg | D54: 500 | E54: 0.2208 | F54: =D54*E54 | G54: Etapa 2, Suma alzada
A55: 4.1.14 | B55: Construcción Brocal Temporal | C55: gl | E55: 116.8831 | F55: =+D55*E55 | G55: Etapa 2, Suma alzada
A56: 4.1.15 | B56: Construcción Brocal Definitivo | C56: gl | D56: 1 | E56: 116.8831 | F56: =D56*E56 | G56: Etapa 2, Suma alzada
A58: 4.2 | B58: Pique 2 Túnel Liner | F58: =+SUM(F59:F73)
A59: 4.2.1 | B59: Excavación | C59: m3 | D59: 234.61 | E59: 2.2078 | F59: =D59*E59 | G59: Etapa 2, Suma alzada | H59: 5% con el cumplimiento de Condiciones contractuales, 85% por avance proporcional y 10% con la recepción provisional de la obra.
A60: 4.2.2 | B60: Retiro excavación y transporte a botadero (geométrico) | C60: m3 | D60: 234.61 | E60: 0.9091 | F60: =D60*E60 | G60: Etapa 2, Suma alzada
A61: 4.2.3 | B61: Montaje Liner (Incluyendo sello entre placas y mortero) | C61: m | D61: 18.7 | E61: 5.7143 | F61: =D61*E61 | G61: Etapa 2, Suma alzada
A62: 4.2.4 | B62: Refuerzo Losa Anillo Fondo de Pique | C62: gl | D62: 1 | E62: 72.7273 | F62: =D62*E62 | G62: Etapa 2, Suma alzada
A63: 4.2.5 | B63: Construcción de Dren | C63: gl | D63: 1 | E63: 46.7532 | F63: =D63*E63 | G63: Etapa 2, Suma alzada
A64: 4.2.6 | B64: Terminaciones | C64: gl | D64: 1 | E64: 38.961 | F64: =D64*E64 | G64: Etapa 2, Suma alzada
A65: 4.2.7 | B65: Cobertura Pique | C65: gl | D65: 1 | E65: 90.9091 | F65: =D65*E65 | G65: Etapa 2, Suma alzada
A66: 4.2.8 | B66: Montaje de Escalas y Plataforma | C66: gl | D66: 1 | E66: 83.1169 | F66: =D66*E66 | G66: Etapa 2, Suma alzada
A67: 4.2.9 | B67: Refuerzo Apertura Pique | C67: gl | D67: 1 | E67: 57.1429 | F67: =D67*E67 | G67: Etapa 2, Suma alzada
A68: 4.2.10 | B68: Shotcrete | C68: m3 | E68: 4.6753 | F68: =+D68*E68 | G68: Etapa 2, Suma alzada
A69: 4.2.11 | B69: Malla | C69: kg | E69: 0.0312 | F69: =+D69*E69 | G69: Etapa 2, Suma alzada
A70: 4.2.12 | B70: Instalación y Monitoreo de Pernos de Convergencia | C70: und | E70: 1.1688 | F70: =+D70*E70 | G70: Etapa 2, Suma alzada
A71: 4.2.13 | B71: Construcción Brocal Temporal | C71: gl | E71: 0.2208 | F71: =+D71*E71 | G71: Etapa 2, Suma alzada
A72: 4.2.14 | B72: Construcción Brocal Definitivo | C72: gl | D72: 1 | E72: 116.8831 | F72: =D72*E72 | G72: Etapa 2, Suma alzada
A74: 4.3 | B74: Pique 3 Túnel Liner | F74: =+SUM(F75:F89)
A75: 4.3.1 | B75: Excavación | C75: m3 | D75: 217.4 | E75: 2.2078 | F75: =D75*E75 | G75: Etapa 2, Suma alzada | H75: 5% con el cumplimiento de Condiciones contractuales, 85% por avance proporcional y 10% con la recepción provisional de la obra.
A76: 4.3.2 | B76: Retiro excavación y transporte a botadero (geométrico) | C76: m3 | D76: 217.4 | E76: 0.9091 | F76: =D76*E76 | G76: Etapa 2, Suma alzada
A77: 4.3.3 | B77: Montaje Liner (Incluyendo sello entre placas y mortero) | C77: m | D77: 17.3 | E77: 5.7143 | F77: =D77*E77 | G77: Etapa 2, Suma alzada
A78: 4.3.4 | B78: Refuerzo Losa Anillo Fondo de Pique | C78: gl | D78: 1 | E78: 72.7273 | F78: =D78*E78 | G78: Etapa 2, Suma alzada
A79: 4.3.5 | B79: Construcción de Dren | C79: gl | D79: 1 | E79: 46.7532 | F79: =D79*E79 | G79: Etapa 2, Suma alzada
A80: 4.3.6 | B80: Terminaciones | C80: gl | D80: 1 | E80: 38.961 | F80: =D80*E80 | G80: Etapa 2, Suma alzada
A81: 4.3.7 | B81: Cobertura Pique | C81: gl | D81: 1 | E81: 90.9091 | F81: =D81*E81 | G81: Etapa 2, Suma alzada
A82: 4.3.8 | B82: Montaje de Escalas y Plataforma | C82: gl | D82: 1 | E82: 83.1169 | F82: =D82*E82 | G82: Etapa 2, Suma alzada
A83: 4.3.9 | B83: Refuerzo Apertura Pique | C83: gl | D83: 1 | E83: 57.1429 | F83: =D83*E83 | G83: Etapa 2, Suma alzada
A84: 4.3.10 | B84: Shotcrete | C84: m3 | E84: 4.6753 | F84: =+D84*E84 | G84: Etapa 2, Suma alzada
A85: 4.3.11 | B85: Malla | C85: kg | E85: 0.0312 | F85: =+D85*E85 | G85: Etapa 2, Suma alzada
A86: 4.3.12 | B86: Instalación y Monitoreo de Pernos de Convergencia | C86: und | E86: 1.1688 | F86: =+D86*E86 | G86: Etapa 2, Suma alzada
A87: 4.3.13 | B87: Construcción Brocal Temporal | C87: gl | E87: 0.2208 | F87: =+D87*E87 | G87: Etapa 2, Suma alzada
A88: 4.3.14 | B88: Construcción Brocal Definitivo | C88: gl | D88: 1 | E88: 116.8831 | F88: =D88*E88 | G88: Etapa 2, Suma alzada
A90: 4.4 | B90: Pique 4 Túnel Liner | F90: =+SUM(F91:F105)
A91: 4.4.1 | B91: Excavación | C91: m3 | D91: 188.24 | E91: 2.2078 | F91: =D91*E91 | G91: Etapa 2, Suma alzada | H91: 5% con el cumplimiento de Condiciones contractuales, 85% por avance proporcional y 10% con la recepción provisional de la obra.
A92: 4.4.2 | B92: Retiro excavación y transporte a botadero (geométrico) | C92: m3 | D92: 188.24 | E92: 0.9091 | F92: =D92*E92 | G92: Etapa 2, Suma alzada
A93: 4.4.3 | B93: Montaje Liner (Incluyendo sello entre placas y mortero) | C93: m | D93: 15 | E93: 5.7143 | F93: =D93*E93 | G93: Etapa 2, Suma alzada
A94: 4.4.4 | B94: Refuerzo Losa Anillo Fondo de Pique | C94: gl | D94: 1 | E94: 72.7273 | F94: =D94*E94 | G94: Etapa 2, Suma alzada
A95: 4.4.5 | B95: Construcción de Dren | C95: gl | D95: 1 | E95: 46.7532 | F95: =D95*E95 | G95: Etapa 2, Suma alzada
A96: 4.4.6 | B96: Terminaciones | C96: gl | D96: 1 | E96: 38.961 | F96: =D96*E96 | G96: Etapa 2, Suma alzada
A97: 4.4.7 | B97: Cobertura Pique | C97: gl | D97: 1 | E97: 90.9091 | F97: =D97*E97 | G97: Etapa 2, Suma alzada
A98: 4.4.8 | B98: Montaje de Escalas y Plataforma | C98: gl | D98: 1 | E98: 83.1169 | F98: =D98*E98 | G98: Etapa 2, Suma alzada
A99: 4.4.9 | B99: Refuerzo Apertura Pique | C99: gl | D99: 1 | E99: 57.1429 | F99: =D99*E99 | G99: Etapa 2, Suma alzada
A100: 4.4.10 | B100: Shotcrete | C100: m3 | E100: 4.6753 | F100: =+D100*E100 | G100: Etapa 2, Suma alzada
A101: 4.4.11 | B101: Malla | C101: kg | E101: 0.0312 | F101: =+D101*E101 | G101: Etapa 2, Suma alzada
A102: 4.4.12 | B102: Instalación y Monitoreo de Pernos de Convergencia | C102: und | E102: 1.1688 | F102: =+D102*E102 | G102: Etapa 2, Suma alzada
A103: 4.4.13 | B103: Construcción Brocal Temporal | C103: gl | E103: 0.2208 | F103: =+D103*E103 | G103: Etapa 2, Suma alzada
A104: 4.4.14 | B104: Construcción Brocal Definitivo | C104: gl | D104: 1 | E104: 116.8831 | F104: =D104*E104 | G104: Etapa 2, Suma alzada
A106: 4.5 | B106: Pique 5 Túnel Liner | F106: =+SUM(F107:F121)
A107: 4.5.1 | B107: Excavación | C107: m3 | D107: 191.51 | E107: 2.2078 | F107: =D107*E107 | G107: Etapa 2, Suma alzada | H107: 5% con el cumplimiento de Condiciones contractuales, 85% por avance proporcional y 10% con la recepción provisional de la obra.
A108: 4.5.2 | B108: Retiro excavación y transporte a botadero (geométrico) | C108: m3 | D108: 191.51 | E108: 0.9091 | F108: =D108*E108 | G108: Etapa 2, Suma alzada
A109: 4.5.3 | B109: Montaje Liner (Incluyendo sello entre placas y mortero) | C109: m | D109: 15.2 | E109: 5.7143 | F109: =D109*E109 | G109: Etapa 2, Suma alzada
A110: 4.5.4 | B110: Refuerzo Losa Anillo Fondo de Pique | C110: gl | D110: 1 | E110: 72.7273 | F110: =D110*E110 | G110: Etapa 2, Suma alzada
...

Sheet B) Detalle C. Ind., GG y Utilid
A2: ANEXO N°
A3: =+'Resumen Oferta'!B3
A4: DESGLOSE DE COSTO INDIRECTO, GASTOS GENERALES Y UTILIDADES
A7: N° | B7: Ítem | C7: Unidad | D7: Cantidad | E7: Tiempo | F7: Precio Unitario | G7: Total UF | H7: Pago
A8: 1.0 | B8: Costos Indirectos de Obra | G8: =+G9+G12+G23+G29+G33
A9: 1.1 | B9: Servicio de Vigilancia de Obra | G9: =+SUM(G10:G11)
A10: 1.1.1 | B10: Servicio de vigilancia 24 horas, incluye guardias, insumos y garita de guardias habilitada | C10: mes | D10: 1 | E10: 24 | F10: 100 | G10: =+D10*E10*F10 | H10: 5% con el cumplimiento de Condiciones contractuales, 85% por avance proporcional y 10% con la recepción provisional de la obra | I10: REF: Servicio vigilancia 24h externalizado
A12: 1.2 | B12: Personal Indirecto | G12: =+SUM(G13:G22)
A13: 1.2.1 | B13: Administrador | C13: mes | D13: 1 | E13: 24 | F13: 150 | G13: =+D13*E13*F13 | H13: 5% con el cumplimiento de Condiciones contractuales, 85% por avance proporcional y 10% con la recepción provisional de la obra | I13: REF: 1 Administrador (~$5.8M CLP/mes)
A14: 1.2.2 | B14: Jefe de Terreno | C14: mes | D14: 1 | E14: 24 | F14: 120 | G14: =+D14*E14*F14 | I14: REF: 1 Jefe de Terreno (~$4.6M CLP/mes)
A15: 1.2.3 | B15: Supervisor | C15: mes | D15: 2 | E15: 24 | F15: 90 | G15: =+D15*E15*F15 | I15: REF: 2 Supervisores en turnos
A16: 1.2.4 | B16: Encargado de Prevención de Riesgos | C16: mes | D16: 1 | E16: 24 | F16: 80 | G16: =+D16*E16*F16 | I16: REF: 1 Encargado Prevencion Riesgos
A17: 1.2.5 | B17: Encargado de Medio Ambiente | C17: mes | D17: 1 | E17: 24 | F17: 70 | G17: =+D17*E17*F17 | I17: REF: 1 Encargado Medio Ambiente
A18: 1.2.6 | B18: Topógrafo | C18: mes | D18: 1 | E18: 24 | F18: 80 | G18: =+D18*E18*F18 | I18: REF: 1 Topografo
A19: 1.2.7 | B19: Trazador | C19: mes | D19: 1 | E19: 24 | F19: 55 | G19: =+D19*E19*F19 | I19: REF: 1 Trazador
A20: 1.2.8 | B20: Bodeguero | C20: mes | D20: 1 | E20: 24 | F20: 50 | G20: =+D20*E20*F20 | I20: REF: 1 Bodeguero
A21: 1.2.9 | B21: Otros (Desglosar)
A23: 1.3 | B23: Maquinarias, Equipos y Vehículos (Desglosar) | G23: =+SUM(G24:G28)
A24: 1.3.1 | B24: Camioneta | C24: und | D24: 3 | E24: 24 | F24: 35 | G24: =+D24*E24*F24 | H24: 5% con el cumplimiento de Condiciones contractuales, 85% por avance proporcional y 10% con la recepción provisional de la obra | I24: REF: 3 Camionetas operativas
A25: 1.3.2 | B25: Fletes | C25: und | D25: 1 | E25: 24 | F25: 50 | G25: =+D25*E25*F25 | I25: REF: Fletes mensuales
A26: 1.3.3 | B26: Andamios | C26: gl | D26: 1 | E26: 24 | F26: 30 | G26: =+D26*E26*F26 | I26: REF: Arriendo andamios
A27: 1.3.4 | B27: Maquinarias y equipos menores | C27: gl | D27: 1 | E27: 24 | F27: 80 | G27: =+D27*E27*F27 | I27: REF: Equipos menores (grupos, compresor)
A29: 1.4 | B29: Gastos de Disposición de Resíduos | G29: =+SUM(G30:G32)
A30: 1.4.1 | B30: Disposición de Resíduos | C30: gl | D30: 1 | E30: 24 | F30: 50 | G30: =+D30*E30*F30 | H30: 5% con el cumplimiento de Condiciones contractuales, 85% por avance proporcional y 10% con la recepción provisional de la obra | I30: REF: Disposicion residuos sólidos
A31: 1.4.2 | B31: Disposición de Excedentes de la Obra | C31: gl | D31: 1 | E31: 24 | F31: 120 | G31: =+D31*E31*F31 | I31: REF: Disposicion excedentes excavación
A33: 1.6 | B33: Otros (Desglosar) | G33: =+SUM(G34:G45)
A34: 1.6.1 | G34: =+D34*E34*F34 | H34: 5% con el cumplimiento de Condiciones contractuales, 85% por avance proporcional y 10% con la recepción provisional de la obra
A35: 1.6.2 | G35: =+D35*E35*F35
A36: 1.6.3 | G36: =+D36*E36*F36
A38: 1.7 | B38: Cobros por Cambios Previsto. Costo por semana de retraso del Mandante en la entrega de los Permisos del Mandante | G38: =+SUM(G39:G45)
A39: 1.7.1 | B39: Costo único a cobrar por mes de retraso del Mandante en su plazo de entrega de los Permisos del Mandante, por sobre los 210 días establecidos en las Bases Técnicas | C39: semana | D39: 4 | G39: =+D39*E39*F39 | H39: Partida a precio unitario 90% por avance proporcional y 10% con la recepción provisional de la obra
A41: 1.8 | B41: Cobros por Cambios Previsto. Paralizaciones por responsabilidad del Mandante [definiciones en Bases Técnicas] | G41: =+SUM(G42:G47)
A42: 1.8.1 | B42: Costo de Desmovilización de Personal de un frente de trabajo. | C42: gl | D42: 3 | G42: =+D42*E42*F42 | H42: Partida a precio unitario 90% por avance proporcional y 10% con la recepción provisional de la obra
A43: 1.8.2 | B43: Costo de Mantrener la Instalación de Faenas y la Vigilancia durante la paralización | C43: semana | D43: 10 | G43: =+D43*E43*F43 | H43: Partida a precio unitario 90% por avance proporcional y 10% con la recepción provisional de la obra
A44: 1.8.3 | B44: Costo de Extensión de Plazos de toda la Obra por Razones del Mandante, descontados los retrasos del Contratista | C44: semana | D44: 10 | G44: =+D44*E44*F44 | H44: Partida a precio unitario 90% por avance proporcional y 10% con la recepción provisional de la obra
A46: 2.0 | B46: Gastos Generales | G46: =+SUM(G47:G51)
A47: 2.1 | B47: Aporte a Oficina Central | C47: gl | D47: 1 | E47: 1 | F47: 3200 | G47: =+D47*E47*F47 | H47: 5% con el cumplimiento de Condiciones contractuales, 85% por avance proporcional y 10% con la recepción provisional de la obra | I47: REF: Aporte oficina central ~4.4% directo
A48: 2.2 | B48: Gastos Financieros | C48: gl | D48: 1 | E48: 1 | F48: 1800 | G48: =+D48*E48*F48 | I48: REF: Gastos financieros ~2.5% directo
A49: 2.3 | B49: Boletas de Garantía y Seguros | C49: gl | D49: 1 | E49: 1 | F49: 1200 | G49: =+D49*E49*F49 | I49: REF: Boletas garantia + seguros ~1.6% directo
A50: 2.4 | B50: Otros (Desglosar)
A52: 3.0 | B52: Utilidades | G52: =+SUM(G53:G54)
A53: 3.1 | B53: Utilidades del Contratista | C53: gl | D53: 1 | E53: 1 | F53: 8000 | G53: =+D53*E53*F53 | H53: 5% con el cumplimiento de Condiciones contractuales, 85% por avance proporcional y 10% con la recepción provisional de la obra | I53: REF: Utilidad contratista ~11% directo
B56: TOTAL COSTO INDIRECTO | G56: =+G8
B57: TOTAL GASTOS GENERALES | G57: =+G46
B58: TOTAL UTILIDAD | G58: =+G52
F67: Firma y Timbre
F68: Representante Legal del Proponente
A72: ⚠ Valores en salmón (cantidades, tiempos, precios) son REFERENCIALES para plazo 24 meses. Contratista debe ajustar a su estructura organizacional y plazo real.

Sheet Análisis de Precios
A1: ANÁLISIS DE PRECIOS — TÚNEL LAT VITACURA-PROVIDENCIA
A2: UF referencial: 38,500 CLP (mayo 2026) | Generado: 2026-05-19
A3: ⚠ SUPUESTO: cantidades sección 5 calculadas para 1 túnel Ø2.21m por tramo. Si la licitación requiere 2 túneles paralelos, multiplicar cantidades 5.x por 2.
A5: 1. CUBICACIÓN REALIZADA (cantidades pre-llenadas en hoja A)
A6: Partida | B6: Cant. | C6: Unidad | D6: Ítems licitación | E6: UF est. medio | F6: Fuente / Cómo se calculó
A7: Excavación pique | B7: 1770.35 | C7: m3 | D7: 4.1.1 | E7: 4,868 UF | F7: área(12.57m²) × profundidad(20m)
A8: Retiro excavación | B8: 1770.35 | C8: m3 | D8: 4.1.2 | E8: 2,036 UF | F8: igual excavación — flete botadero
A9: Montaje liner pique | B9: 140.88 | C9: m | D9: 4.1.3 | E9: 845 UF | F9: profundidad pique (20m = 20 anillos)
A10: Montaje escalas+plataformas | B10: 9 | C10: gl | D10: 4.1.8 | E10: 810 UF | F10: 1 gl por pique (STM aporta estructuras)
A11: Brocal definitivo | B11: 9 | C11: gl | D11: 4.1.15 | E11: 1,035 UF | F11: 1 gl por pique
A12: Excavación túnel | B12: 9414.22 | C12: m3 | D12: 5.1-5.8 | E12: 47,071 UF | F12: área(3.84m²) × longitud / 8 tramos
A13: Montaje liner túnel Ø2.21m | B13: 2454.2 | C13: m | D13: 5.1-5.8 | E13: 11,657 UF | F13: longitud tunel / 8 tramos
A14: Radier túnel H30 | B14: 813.57 | C14: m3 | D14: 5.1-5.8 | E14: 6,915 UF | F14: área × espesor(0.15m)
A16: 2. NO CUBICADO — Requiere estudio específico o suma alzada del contratista
A17: Ítem licitación | B17: Unidad | C17: Razón / Recomendación
A18: 4.x.10 Shotcrete | B18: m³ | C18: Depende de clasificación RMR del terreno (geotecnia)
A19: 4.x.11 Malla | B19: kg | C19: Diseño geotécnico — varía según tipo de suelo
A20: 4.x.12 Pernos de convergencia | B20: und | C20: Análisis convergencia-confinamiento requerido
A21: 4.x.4 Refuerzo Losa Anillo Fondo | B21: gl | C21: Suma alzada — cotización directa contratista
A22: 4.x.5 Construcción Dren | B22: gl | C22: Suma alzada — cotización directa contratista
A23: 4.x.6 Terminaciones | B23: gl | C23: Suma alzada — cotización directa contratista
A24: 4.x.7 Cobertura pique | B24: gl | C24: Suma alzada — cotización directa contratista
A25: 4.x.9 Refuerzo apertura | B25: gl | C25: Suma alzada — cotización directa contratista
A26: 4.x.14 Brocal temporal | B26: gl | C26: Suma alzada — cotización directa contratista
A27: Sec. 2 Liner pique Ø4m + liner túnel Ø2.21m | B27: — | C27: Aporte STM: mandante suministra el material liner, contratista instala (ítems 4.x.3, 5.x.3)
A28: Sec. 2 Escalas y plataformas (estructura) | B28: — | C28: Aporte STM: mandante suministra estructura, contratista monta (ítem 4.x.8)
... A32: Sec. 3 Instalación de Faenas | B32: gl | C32: Suma alzada. IF SS Vitacura (STM-IF-20251009): 3 etapas (Túnel Liner / TL+OOEE / OOCC+OOEE). Contenido típico: contenedores oficinas/baños/bodega, compresor, winche, minicargador, acopio liner.
A34: 3. PRECIOS DE REFERENCIA MERCADO CHILE 2026 (estimados — solicitar cotización formal)
A35: Partida | B35: Unidad | C35: UF mín/un | D35: UF máx/un | E35: CLP mín/un (aprox) | F35: Referencia
A36: Excavación pique Ø4m | B36: m³ | C36: 2.00 | D36: 3.50 | E36: $77,000 – $134,750 | F36: ONDAC 2026
A37: Retiro excavación pique | B37: m³ | C37: 0.80 | D37: 1.50 | E37: $30,800 – $57,750 | F37: Mercado Santiago
A38: Montaje liner pique Ø4m (solo inst.) | B38: m | C38: 4.00 | D38: 8.00 | E38: $154,000 – $308,000 | F38: Est. mercado
A39: Shotcrete en pique | B39: m³ | C39: 4.50 | D39: 7.00 | E39: $173,250 – $269,500 | F39: ONDAC 2026
A40: Malla electrosoldada | B40: kg | C40: 0.03 | D40: 0.05 | E40: $1,155 – $1,925 | F40: ONDAC 2026
A41: Montaje escalas+plataformas | B41: gl | C41: 60.00 | D41: 120.00 | E41: $2,310,000 – $4,620,000 | F41: Est. mercado/pique
A42: Brocal definitivo | B42: gl | C42: 80.00 | D42: 150.00 | E42: $3,080,000 – $5,775,000 | F42: Est. mercado
A43: Excavación túnel Ø2.21m | B43: m³ | C43: 3.50 | D43: 6.00 | E43: $134,750 – $231,000 | F43: ONDAC 2026 tunel urbano
A44: Montaje liner túnel Ø2.21m | B44: m | C44: 3.50 | D44: 6.00 | E44: $134,750 – $231,000 | F44: Est. instalación
A45: Radier túnel H30 | B45: m³ | C45: 7.00 | D45: 10.00 | E45: $269,500 – $385,000 | F45: ONDAC 2026
A46: Extractor Soler-Palau TGT/6-1409 (37kW) — 2 un | B46: un | C46: 800.00 | D46: 1200.00 | E46: $30,800,000 – $46,200,000 | F46: STM38110 §3.14 — suministro STM, instalación contratista
A47: Jet Fan S&P TJHT/2/4-315-C (1.1kW) — N un | B47: un | C47: 20.00 | D47: 40.00 | E47: $770,000 – $1,540,000 | F47: STM38110 §2.12 — suministro STM, cant. pendiente STM38109
A49: 4. ANÁLISIS DE SENSATEZ — PROYECTO COMPLETO (9 piques + 8 tramos)
A50: Partida | B50: Cant. | C50: UF/un Mín | D50: UF/un Máx | E50: Subtotal Mín (UF) | F50: Subtotal Máx (UF)
A51: Excavación piques | B51: 1770.3 | C51: 2.00 | D51: 3.50 | E51: 3,540.7 | F51: 6,196.2
A52: Retiro excav. piques | B52: 1770.3 | C52: 0.80 | D52: 1.50 | E52: 1,416.3 | F52: 2,655.5
A53: Montaje liner piques | B53: 140.9 | C53: 4.00 | D53: 8.00 | E53: 563.6 | F53: 1,127.2
A54: Montaje escalas+plataformas | B54: 9 | C54: 60.00 | D54: 120.00 | E54: 540.0 | F54: 1,080.0
A55: Brocal definitivo | B55: 9 | C55: 80.00 | D55: 150.00 | E55: 720.0 | F55: 1,350.0
A56: Excavación túnel | B56: 9414.2 | C56: 3.50 | D56: 6.00 | E56: 32,949.8 | F56: 56,485.3
A57: Montaje liner túnel | B57: 2454.2 | C57: 3.50 | D57: 6.00 | E57: 8,589.7 | F57: 14,725.2
A58: Radier H30 | B58: 813.6 | C58: 7.00 | D58: 10.00 | E58: 5,695.1 | F58: 8,135.8
A59: TOTAL ÍTEMS CUBICADOS | E59: 54,015 UF (~$2079M CLP) | F59: 91,755 UF (~$3532M CLP)
A60: ⚠ NOTA: El rango anterior NO incluye shotcrete, malla, pernos, terminaciones, instalación de faenas ni actividades previas (Sec. 1, 3) — típicamente +30-50% adicional.
A62: 5. CANTIDADES PRE-EXISTENTES EN TEMPLATE (de la licitación original)
A63: Ítem | B63: Descripción | C63: Unidad | D63: Cantidad original | F63: Fuente
A64: 5.1.4 | B64: Pernos frente fibra vidrio 4m (eventual) | C64: und | D64: 39.54 | F64: Cuadro precios STM rev.1 06/04/2026
A65: 5.1.5 | B65: Shotcrete frente (eventual) | C65: m³ | D65: 19.77 | F65: Cuadro precios STM rev.1 06/04/2026
A66: 5.1.6 | B66: Paraguas micropilotes (eventual) | C66: und | D66: 24 | F66: Cuadro precios STM rev.1 06/04/2026
A67: 5.2.4–5.8.4 | B67: Pernos frente (tramos 2-8) | C67: und | D67: 36-36 por tramo | F67: Cuadro precios STM rev.1 06/04/2026
A68: 7.1 | B68: Base binder asfalto | C68: m² | D68: 317.61 | F68: Cuadro precios STM rev.1 06/04/2026
A69: 7.2 | B69: Base chancada CBR80 | C69: m³ | D69: 66.7 | F69: Cuadro precios STM rev.1 06/04/2026
A70: 7.3 | B70: Calzada con tratamiento asfaltico | C70: m² | D70: 317.61 | F70: Cuadro precios STM rev.1 06/04/2026
A71: 7.5 | B71: Excavación dura y transporte botadero | C71: m³ | D71: 343.02 | F71: Cuadro precios STM rev.1 06/04/2026
A72: 7.10 | B72: Entibación excavaciones | C72: m | D72: 90.75 | F72: Cuadro precios STM rev.1 06/04/2026
A73: 7.11 | B73: Reposición áreas verdes | C73: m² | D73: 60 | F73: Cuadro precios STM rev.1 06/04/2026
A74: 7.12 | B74: Reposición soleras | C74: m | D74: 40 | F74: Cuadro precios STM rev.1 06/04/2026
A75: 7.13 | B75: Demolición y reposición veredas | C75: m² | D75: 20 | F75: Cuadro precios STM rev.1 06/04/2026
A76: 13.2 | B76: Retiro y transporte aguas efluentes | C76: m³ | D76: 1000 | F76: Cuadro precios STM rev.1 06/04/2026

Sheet Memoria de Cálculo
A1: MEMORIA DE CÁLCULO — TÚNEL LAT 2×110 kV VITACURA-PROVIDENCIA
A2: Documento generado: 2026-05-19 | Licitación: 2025-25-TX-SS-RM | Mandante: STM
A4: 1. CONSTANTES GEOMÉTRICAS
A5: # | B5: Constante | C5: Fórmula | D5: Valor | E5: Unidad | F5: Fuente
A6: 1.1 | B6: Área sección pique | C6: π × r² = π × (4.0/2)² | D6: 12.5664 | E6: m² | F6: STM38136 Ø interior pique
A7: 1.2 | B7: Área sección túnel liner | C7: π × r² = π × (2.21/2)² | D7: 3.8359 | E7: m² | F7: STM38136 Ø interior liner
A8: 1.3 | B8: Radier H30 volumen por metro | C8: ancho × espesor = 2.21 × 0.15 | D8: 0.3315 | E8: m³/m | F8: Diseño estructural radier túnel
A9: 1.4 | B9: Diámetro fundación pique | C9: 4.20 m externo | D9: 4.20 | E9: m | F9: STM38020 detalle típico
A10: 1.5 | B10: Espesor liner acero A-36 | C10: 5 mm | D10: 0.005 | E10: m | F10: STM38019 §5.1 modelo TL
A11: 1.6 | B11: Espesor revestimiento estándar | C11: Liner 5mm + Shotcrete G-30 95mm | D11: 0.10 | E11: m | F11: STM38019 §5.1 (pp.17)
A12: 1.7 | B12: Espesor zona reforzada (apertura ojo demolición) | C12: Liner + Shotcrete + 2do revestimiento | D12: 0.20 | E12: m | F12: STM38019 §5.1
A13: 1.8 | B13: Avance por anillo (pique y túnel) | C13: Excavación + instalación liner secuencial | D13: 0.46 | E13: m | F13: STM38019 §5.1 Tabla 5
A15: 2. PROFUNDIDADES DE PIQUES — NV terreno - NV invert liner
A16: Pique | B16: NV terreno (m.s.n.m) | C16: NV liner invert (m.s.n.m) | D16: Profundidad (m) | E16: Excavación (m³) | F16: Fuente plano
A17: P1 | B17: 625.06 | C17: 604.97 | D17: 20.09 | E17: 252.46 | F17: STM38020
A18: P2 | B18: 621.50 | C18: 602.83 | D18: 18.67 | E18: 234.61 | F18: STM38020
A19: P3 | B19: 619.18 | C19: 601.88 | D19: 17.30 | E19: 217.4 | F19: STM38020
A20: P4 | B20: 612.91 | C20: 597.93 | D20: 14.98 | E20: 188.24 | F20: STM38021
A21: P5 | B21: 610.70 | C21: 595.46 | D21: 15.24 | E21: 191.51 | F21: STM38021
A22: P6 | B22: 607.39 | C22: 591.88 | D22: 15.51 | E22: 194.9 | F22: STM38022
A23: P7 | B23: 603.15 | C23: 587.53 | D23: 15.62 | E23: 196.29 | F23: STM38022
A24: P8 | B24: 599.00 | C24: 584.59 | D24: 14.41 | E24: 181.08 | F24: STM38023
A25: P9 | B25: 591.18 | C25: 582.12 | D25: 9.06 | E25: 113.85 | F25: STM38023
A26: ⚠ Discrepancia P9: STM38109 §2.4 reporta 9.67m (referencia portal vs NV terreno). Diferencia 0.61m × 12.57m² = ~7.7 m³ excavación adicional si se usa cota portal.
A28: 3. LONGITUDES DE TRAMOS — DM piques sucesivos
A29: Tramo | B29: Entre piques | C29: DM inicio (m) | D29: DM fin (m) | E29: Longitud (m) | F29: Fuente plano
A30: T1 | B30: P1-P2 | C30: 0.0 | D30: 389.0 | E30: 389.0 | F30: STM38020
A31: T2 | B31: P2-P3 | C31: 389.0 | D31: 560.6 | E31: 171.6 | F31: STM38020
A32: T3 | B32: P3-P4 | C32: 560.6 | D32: 955.7 | E32: 395.1 | F32: STM38020
A33: T4 | B33: P4-P5 | C33: 955.7 | D33: 1161.6 | E33: 205.9 | F33: STM38021
A34: T5 | B34: P5-P6 | C34: 1161.6 | D34: 1459.4 | E34: 297.8 | F34: STM38021
A35: T6 | B35: P6-P7 | C35: 1459.4 | D35: 1777.4 | E35: 318.0 | F35: STM38022
A36: T7 | B36: P7-P8 | C36: 1777.4 | D36: 2145.1 | E36: 367.7 | F36: STM38022
A37: T8 | B37: P8-P9 | C37: 2145.1 | D37: 2454.2 | E37: 309.1 | F37: STM38023
A39: 4. FÓRMULAS POR PARTIDA
A40: # | B40: Partida | C40: Fórmula aplicada | D40: Cantidad total | E40: Unidad | F40: Validación
A41: 4.1 | B41: Excavación piques | C41: Σ (12.5664 m² × prof_i) para i=1..9 | D41: 1770.34 | E41: m³ | F41: ✓ Coincide con suma manual
A42: 4.2 | B42: Retiro excavación piques | C42: =Excavación pique (igual volumen al botadero) | D42: 1770.34 | E42: m³ | F42: ✓ = Excavación
A43: 4.3 | B43: Montaje liner pique | C43: Σ profundidad_i para i=1..9 | D43: 140.9 | E43: m | F43: =longitud anillo × cantidad anillos
A44: 4.4 | B44: Refuerzo losa anillo fondo (.4) | C44: 1 gl × 9 piques (suma alzada por pique) | D44: 9 | E44: gl | F44: Cant 1 gl/pique — precio cotizar
A45: 4.5 | B45: Dren / Terminaciones / Cobertura / Refuerzo apertura | C45: 1 gl × 9 piques cada uno (items .5, .6, .7, .9) | D45: 36 | E45: gl | F45: 4 items × 9 piques = 36 gl en total
A46: 4.6 | B46: Montaje escalas+plataformas (.8) | C46: 1 gl × 9 piques (Aporte STM) | D46: 9 | E46: gl | F46: ✓ Una unidad global por pique
A47: 4.7 | B47: Estructura soporte cables SS (.13) | C47: 500 kg × 2 piques (P1, P9) — estimado acero galvanizado | D47: 1000 | E47: kg | F47: Solo SS Vitacura + SS Providencia
A48: 4.8 | B48: Brocal definitivo (.14 / .15) | C48: 1 gl × 9 piques | D48: 9 | E48: gl | F48: P1/P9 → ítem .15; P2-8 → ítem .14
A49: 4.9 | B49: Shotcrete / Malla / Pernos Conv. (.10, .11, .12) | C49: EVENTUAL — Tabla 15 STM38019 medidas auxiliares condicionales | D49: 0 | E49: — | F49: ✓ Eventual: sin cantidad sistemática (Bosc.Cord. Nivel 0)
A50: 5.1 | B50: Excavación túnel | C50: Σ (3.8359 m² × longitud_i) para i=1..8 | D50: 9414.22 | E50: m³ | F50: Verifica: 3.8359 × 2454.2 = 9414.2 ✓
A51: 5.2 | B51: Radier túnel H30 | C51: Σ (0.3315 m³/m × longitud_i) para i=1..8 | D51: 813.58 | E51: m³ | F51: Verifica: 0.3315 × 2454.2 = 813.6 ✓
A52: 5.3 | B52: Monitoreo de Pernos (.8) | C52: 1 gl × 8 tramos | D52: 8 | E52: gl | F52: Item .8 del template (NO instalación cables)
A53: 5.4 | B53: Estructura soporte cables AT túnel (.12) | C53: 20 kg/ml × longitud_i para i=1..8 (acero galvanizado) | D53: 49084 | E53: kg | F53: ⚠ Estimado 20 kg/ml — confirmar diseño bandejas
A54: 5.5 | B54: Pernos frente / Shotcrete / Paraguas (.4, .5, .6) | C54: Cantidades del template original (eventuales) | D54: 0 | E54: — | F54: Cant 'eventual' del cuadro precios STM
A56: 5. EQUIPAMIENTO ELÉCTRICO (Aporte STM — Sección 2 licitación)
A57: # | B57: Equipo | C57: Cantidad | D57: Modelo / specs | E57: Ubicación | F57: Fuente
A58: 5.1 | B58: Jet Fan túnel | C58: 23 | D58: S&P TJHT2/4-315-CN (0.8 kW, 24 N, 4500 m³/h) | E58: Fan1 DM+70 → Fan23 DM+2380, cada 105 m | F58: STM38109 §4.5 + Tabla 4.2 (REV.E 28-01-2026)
A59: 5.2 | B59: Extractor pique | C59: 2 | D59: Soler-Palau TGT/6-1409 (37 kW, 132000 m³/h, Ø1409 mm) | E59: bocas P1 (SS Vitacura) y P9 (SS Providencia) | F59: STM38110 §3.1 + §3.14
A61: 6. SUPUESTOS CRÍTICOS Y VALIDACIONES PENDIENTES
A62: # | B62: Supuesto | C62: Valor usado | D62: Origen | E62: Impacto si cambia | F62: Estado
A63: 6.1 | B63: N° túneles paralelos | C63: 1 | D63: Diseño STM | E63: Multiplicar Sec 5 por N | F63: ✓ Confirmado 1
A64: 6.2 | B64: Estructura soporte cables AT túnel (5.x.12) | C64: 20 kg/ml × 2454m = 49.084 kg | D64: Estimado: 6 cables LAT 2×110kV, bandejas+soportes acero galv. | E64: Si diseño real difiere → ajustar kg/ml | F64: ⚠ Confirmar plano bandejas
A65: 6.3 | B65: Estructura soporte cables SS (4.x.13) | C65: 500 kg × 2 (P1, P9) = 1.000 kg | D65: Estimado por SS — racks, bandejas, terminales | E65: Verificar plano SS Vitacura/Providencia | F65: ⚠ Estimado
A66: 6.4 | B66: Profundidad P9 | C66: 9.06 m (NV) | D66: STM38023 vs STM38109 (9.67m) | E66: Δ excav P9 = 7.7 m³ | F66: ⚠ Discrepancia 0.61m
A67: 6.5 | B67: Diámetro liner interior | C67: 2.21 m | D67: STM38136 vs STM38109 (2.10m) | E67: Δ sección = 0.38 m² (10%) | F67: ✓ 2.21m incluye espesor anillos
A68: 6.6 | B68: Longitud túnel total | C68: 2454.2 m | D68: STM38020-23 suma DM | E68: STM38109 redondea a 2450m | F68: ✓ Diferencia 4.2m (0.17%)
A69: 6.7 | B69: Cantidades 4.x.10-12 (shotcrete/malla/pernos) | C69: EVENTUAL — sin cantidad sistemática | D69: STM38019 §7+§8: Tabla 15 medidas auxiliares condicionales; Boscarding Cording Nivel 0 (deformaciones <1mm) | E69: Solo se aplica si terreno lo requiere | F69: ✓ Eventual confirmado
A70: 6.8 | B70: Items 4.x.4-7, 4.x.9 (suma alzada) | C70: 1 gl × 9 piques cada uno | D70: Refuerzo losa, dren, terminaciones, cobertura, refuerzo apertura | E70: Precios referenciales — cotizar | F70: ⚠ Suma alzada
A71: 6.9 | B71: Monitoreo Pernos (5.x.8) | C71: 1 gl × 8 tramos | D71: Item correcto del template (NO instalación cables — bug v3) | E71: Cant 1 gl/tramo es estándar | F71: ✓ Corregido v4
A72: 6.10 | B72: UF referencial | C72: 38.500 CLP | D72: Mayo 2026 | E72: Actualizar al mes oferta | F72: ✓ Configurable
A73: 6.11 | B73: Altura excavación = profundidad NV | C73: Sí | D73: Convención técnica | E73: Si sump existe → +volumen | F73: ⚠ STM38023 nota 'Nivel -3.50' en P9
... A78: 6.16 | B78: Boscarding Cording (afectaciones) | C78: Nivel 0 (despreciable) en TODOS los cruces | D78: STM38019 §8 — Costanera Norte, Mapocho Limpio, San Carlos, L7 Metro | E78: Sin requerimiento extra de monitoreo intensivo | F78: ✓ Bajo riesgo confirmado
A80: 7. TRAZABILIDAD DE FUENTES (documentos consultados)
A81: # | B81: Documento | C81: Revisión | D81: Datos extraídos | E81: Hoja relevante | F81: —
A82: 7.1 | B82: STM38020 Planta y Perfil | C82: REV.0 | D82: P1, P2, P3 NV + DM tramos T1-T3 | E82: Detalle Costo Directo
A83: 7.2 | B83: STM38021 Planta y Perfil | C83: REV.0 | D83: P4, P5 NV + DM tramos T3-T5 | E83: Detalle Costo Directo
A84: 7.3 | B84: STM38022 Planta y Perfil | C84: REV.0 | D84: P6, P7 NV + DM tramos T5-T7 | E84: Detalle Costo Directo
A85: 7.4 | B85: STM38023 Planta y Perfil | C85: REV.0 | D85: P8, P9 NV + DM tramos T7-T8 | E85: Detalle Costo Directo
A86: 7.5 | B86: STM38109 Memoria Ventilación | C86: REV.E 28-01-2026 | D86: 23 jet fans S&P TJHT2/4-315-CN, ubicación Tabla 4.2 | E86: Sec 5 supuestos
A87: 7.6 | B87: STM38110 ETP Equipos Ventilación | C87: REV.0 14-11-2025 | D87: 2 extractores Soler-Palau TGT/6-1409, modelo jet fan | E87: Sec 5 supuestos
A88: 7.7 | B88: STM38019 Informe No-Afecciones (NATM, FLAC3D) | C88: REV.0 15-01-2026 | D88: Estratigrafía H1-H3 + Parámetros geotécnicos + Espesor revestimiento (10cm estándar, 20cm reforzado) + Avance 0.46m + Tabla 15 medidas eventuales + Boscarding Cording Nivel 0 | E88: Sec 1 constantes + Sec 6 supuestos
A89: 7.8 | B89: STM38136 Planos eléctricos | C89: REV.1 06/04/2026 | D89: Ø interior pique 4.0m, Ø interior liner 2.21m | E89: Sec 1 constantes
A90: 7.9 | B90: BAE Licitación 2025-25-TX-SS-RM | C90: REV.0 13/04/2026 | D90: Estructura items 4.x y 5.x | E90: A) Detalle
A91: 7.10 | B91: IF SS Vitacura | C91: 20251009 (3 etapas) | D91: Composición Instalación de Faenas | E91: Sec 3 supuestos suma alzada
A93: 8. RESUMEN TOTALES CUBICADOS
A94: # | B94: Concepto | C94: Cantidad | D94: Unidad | E94: — | F94: —
A95: 8.1 | B95: Excavación piques (suma) | C95: 1770.34 | D95: m³
A96: 8.2 | B96: Excavación túnel (suma) | C96: 9414.22 | D96: m³
A97: 8.3 | B97: Liner pique (suma profundidades) | C97: 140.9 | D97: m
A98: 8.4 | B98: Liner túnel (longitud total) | C98: 2454.2 | D98: m
A99: 8.5 | B99: Radier H30 | C99: 813.58 | D99: m³
A100: 8.6 | B100: Estructura soporte cables AT túnel (5.x.12) | C100: 49084 | D100: kg | E100: (20 kg/ml × 2454m)
A101: 8.7 | B101: Estructura soporte cables SS (4.x.13) | C101: 1000 | D101: kg | E101: (500 kg × P1+P9 = 1000 kg)
A102: 8.8 | B102: Escalas+plataformas | C102: 9 | D102: gl
A103: 8.9 | B103: Brocales definitivos | C103: 9 | D103: gl
A104: 8.10 | B104: Monitoreo de Pernos (5.x.8) | C104: 8 | D104: gl | E104: (1 gl × 8 tramos)
A105: 8.11 | B105: Items suma alzada piques (4.x.4-7, 4.x.9) | C105: 45 | D105: gl | E105: (5 items × 9 piques = 45 gl)
A107: 9. RACIONALES COSTOS INDIRECTOS, GG Y UTILIDAD (hoja B)
A108: # | B108: Concepto | C108: Cantidad | D108: Tiempo | E108: Precio UF/u | F108: Subtotal UF / Justificación
A109: 9.0 | B109: Plazo referencial proyecto | C109: — | D109: 24 meses | E109: — | F109: Estimado tunneling 2.45km — verificar Bases Técnicas
A110: 9.1 | B110: Vigilancia 24h externalizada | C110: 1 | D110: 24 m | E110: 100 | F110: 2,400 UF — servicio integral 4 guardias rotación
A111: 9.2 | B111: Personal indirecto (8 personas, sueldo UF/mes) | C111: — | D111: 24 m | E111: — | F111: 18,840 UF total. Admin 150, JT 120, 2×Sup 90, Prev 80, MA 70, Topo 80, Tra 55, Bod 50 UF/mes (mid-range Chile 2026)
A112: 9.3 | B112: Maquinarias y vehículos | C112: — | D112: 24 m | E112: — | F112: 6,360 UF — 3 camionetas (35), fletes (50), andamios (30), equipos menores (80) UF/mes
A113: 9.4 | B113: Disposición residuos + excedentes | C113: — | D113: 24 m | E113: — | F113: 4,080 UF — residuos sólidos (50), excedentes excavación (120) UF/mes
...
